LICENSE.txt
MANIFEST.in
README.md
setup.cfg
setup.py
lajobsparser/__init__.py
lajobsparser/experience_parser.py
lajobsparser/parse_job_paths.py
lajobsparser/parse_jobs.py
lajobsparser/test_experience_parser.py
lajobsparser.egg-info/PKG-INFO
lajobsparser.egg-info/SOURCES.txt
lajobsparser.egg-info/dependency_links.txt
lajobsparser.egg-info/requires.txt
lajobsparser.egg-info/top_level.txt