Metadata-Version: 2.1
Name: lajobsparser
Version: 0.3.0
Summary: Parser for Los Angeles city jobs bulletins
Home-page: https://github.com/gavinln/lajobsparser
Author: Gavin Noronha
Author-email: gavinln@hotmail.com
License: UNKNOWN
Project-URL: Bug Reports, https://github.com/gavinln/lajobsparser/issues
Project-URL: Source, https://github.com/gavinln/lajobsparser/
Keywords: kaggle text processing
Platform: UNKNOWN
Classifier: Development Status :: 3 - Alpha
Classifier: Intended Audience :: Developers
Classifier: Topic :: Software Development :: Build Tools
Classifier: License :: OSI Approved :: MIT License
Classifier: Programming Language :: Python :: 3.6
Classifier: Programming Language :: Python :: 3.7
Requires-Python: >=3.6, <4
